{
  "main": {
    "id": "4803a0c783461fcf",
    "type": "split",
    "children": [
      {
        "id": "7e4eff4684979bda",
        "type": "tabs",
        "children": [
          {
            "id": "a39f77d66e3724d6",
            "type": "leaf",
            "state": {
              "type": "graph",
              "state": {},
              "icon": "lucide-git-fork",
              "title": "Graph view"
            }
          },
          {
            "id": "229ca79be309a4a2",
            "type": "leaf",
            "state": {
              "type": "markdown",
              "state": {
                "file": "Literature Mapping Process.md",
                "mode": "source",
                "source": false
              },
              "icon": "lucide-file",
              "title": "Literature Mapping Process"
            }
          },
          {
            "id": "f46f39e5c680cd97",
            "type": "leaf",
            "state": {
              "type": "markdown",
              "state": {
                "file": "Dimensions/CSI (Cue-Stimulus Interval).md",
                "mode": "source",
                "source": false
              },
              "icon": "lucide-file",
              "title": "CSI (Cue-Stimulus Interval)"
            }
          },
          {
            "id": "2ec9460cafa27a24",
            "type": "leaf",
            "state": {
              "type": "markdown",
              "state": {
                "file": "Effects/PRP Effect.md",
                "mode": "source",
                "source": false
              },
              "icon": "lucide-file",
              "title": "PRP Effect"
            }
          },
          {
            "id": "a5d7190205717172",
            "type": "leaf",
            "state": {
              "type": "markdown",
              "state": {
                "file": "Effects/Switch Cost.md",
                "mode": "source",
                "source": false
              },
              "icon": "lucide-file",
              "title": "Switch Cost"
            }
          },
          {
            "id": "5d1c6df2d368a2f9",
            "type": "leaf",
            "state": {
              "type": "markdown",
              "state": {
                "file": "Parametric Design Space.md",
                "mode": "source",
                "source": false
              },
              "icon": "lucide-file",
              "title": "Parametric Design Space"
            }
          },
          {
            "id": "7e8c4a2702b895bd",
            "type": "leaf",
            "state": {
              "type": "markdown",
              "state": {
                "file": "Dimensions/Response Set Overlap.md",
                "mode": "source",
                "source": false
              },
              "icon": "lucide-file",
              "title": "Response Set Overlap"
            }
          },
          {
            "id": "1954a04ce455d0fd",
            "type": "leaf",
            "state": {
              "type": "markdown",
              "state": {
                "file": "Parametric Design Space.md",
                "mode": "source",
                "source": false
              },
              "icon": "lucide-file",
              "title": "Parametric Design Space"
            }
          },
          {
            "id": "a295c08ce06ef455",
            "type": "leaf",
            "state": {
              "type": "markdown",
              "state": {
                "file": "Parametric Design Space.md",
                "mode": "source",
                "source": false
              },
              "icon": "lucide-file",
              "title": "Parametric Design Space"
            }
          },
          {
            "id": "902c7858e2cdf217",
            "type": "leaf",
            "state": {
              "type": "markdown",
              "state": {
                "file": "Theoretical Concepts/Bottleneck Theories.md",
                "mode": "source",
                "source": false
              },
              "icon": "lucide-file",
              "title": "Bottleneck Theories"
            }
          },
          {
            "id": "60b467d8cb694704",
            "type": "leaf",
            "state": {
              "type": "markdown",
              "state": {
                "file": "Task Switching.md",
                "mode": "source",
                "source": false
              },
              "icon": "lucide-file",
              "title": "Task Switching"
            }
          },
          {
            "id": "b4b2c265dd9b8a62",
            "type": "leaf",
            "state": {
              "type": "markdown",
              "state": {
                "file": "Theoretical Concepts/Task-Set Inertia.md",
                "mode": "source",
                "source": false
              },
              "icon": "lucide-file",
              "title": "Task-Set Inertia"
            }
          },
          {
            "id": "642a07d66449224f",
            "type": "leaf",
            "state": {
              "type": "markdown",
              "state": {
                "file": "Dimensions/Response Set Overlap.md",
                "mode": "source",
                "source": false
              },
              "icon": "lucide-file",
              "title": "Response Set Overlap"
            }
          },
          {
            "id": "c8def280f391fb65",
            "type": "leaf",
            "state": {
              "type": "markdown",
              "state": {
                "file": "Effects/Mixing Cost.md",
                "mode": "source",
                "source": false
              },
              "icon": "lucide-file",
              "title": "Mixing Cost"
            }
          },
          {
            "id": "fcbb4fc7cdef2359",
            "type": "leaf",
            "state": {
              "type": "graph",
              "state": {},
              "icon": "lucide-git-fork",
              "title": "Graph view"
            }
          }
        ],
        "currentTab": 14
      }
    ],
    "direction": "vertical"
  },
  "left": {
    "id": "2cd22291e5e9556a",
    "type": "split",
    "children": [
      {
        "id": "bb17052a31db262d",
        "type": "tabs",
        "children": [
          {
            "id": "b3b7475c4c82ea5c",
            "type": "leaf",
            "state": {
              "type": "file-explorer",
              "state": {
                "sortOrder": "alphabetical",
                "autoReveal": false
              },
              "icon": "lucide-folder-closed",
              "title": "Files"
            }
          },
          {
            "id": "d6deaa8e1c1576bb",
            "type": "leaf",
            "state": {
              "type": "search",
              "state": {
                "query": "",
                "matchingCase": false,
                "explainSearch": false,
                "collapseAll": false,
                "extraContext": false,
                "sortOrder": "alphabetical"
              },
              "icon": "lucide-search",
              "title": "Search"
            }
          },
          {
            "id": "48cabb0130e64099",
            "type": "leaf",
            "state": {
              "type": "bookmarks",
              "state": {},
              "icon": "lucide-bookmark",
              "title": "Bookmarks"
            }
          }
        ]
      }
    ],
    "direction": "horizontal",
    "width": 300
  },
  "right": {
    "id": "faf32e6d3477f562",
    "type": "split",
    "children": [
      {
        "id": "d27362ca152fe6e4",
        "type": "tabs",
        "children": [
          {
            "id": "47f6b96919262032",
            "type": "leaf",
            "state": {
              "type": "backlink",
              "state": {
                "collapseAll": false,
                "extraContext": false,
                "sortOrder": "alphabetical",
                "showSearch": false,
                "searchQuery": "",
                "backlinkCollapsed": false,
                "unlinkedCollapsed": true
              },
              "icon": "links-coming-in",
              "title": "Backlinks"
            }
          },
          {
            "id": "c3908d92a576a016",
            "type": "leaf",
            "state": {
              "type": "outgoing-link",
              "state": {
                "linksCollapsed": false,
                "unlinkedCollapsed": true
              },
              "icon": "links-going-out",
              "title": "Outgoing links"
            }
          },
          {
            "id": "7f4001b3eeb0b85e",
            "type": "leaf",
            "state": {
              "type": "tag",
              "state": {
                "sortOrder": "frequency",
                "useHierarchy": true,
                "showSearch": false,
                "searchQuery": ""
              },
              "icon": "lucide-tags",
              "title": "Tags"
            }
          },
          {
            "id": "df0e1eac014c9f4c",
            "type": "leaf",
            "state": {
              "type": "outline",
              "state": {
                "followCursor": false,
                "showSearch": false,
                "searchQuery": ""
              },
              "icon": "lucide-list",
              "title": "Outline"
            }
          }
        ],
        "currentTab": 3
      }
    ],
    "direction": "horizontal",
    "width": 300
  },
  "left-ribbon": {
    "hiddenItems": {
      "switcher:Open quick switcher": false,
      "graph:Open graph view": false,
      "canvas:Create new canvas": false,
      "daily-notes:Open today's daily note": false,
      "templates:Insert template": false,
      "command-palette:Open command palette": false
    }
  },
  "active": "fcbb4fc7cdef2359",
  "lastOpenFiles": [
    "Theoretical Concepts/Bottleneck Theories.md",
    "Dual-Task Performance & PRP.md",
    "Effects/Backward Crosstalk Effect (BCE).md",
    "Theoretical Concepts/Crosstalk.md",
    "Papers/Koch et al. (2018).md",
    "Untitled.md",
    "Effects/Mixing Cost.md",
    "Dimensions/Stimulus Bivalence & Congruency.md",
    "Theoretical Concepts/Capacity Sharing.md",
    "Theoretical Concepts/Task-Set Reconfiguration.md",
    "Theoretical Concepts/Task-Set Inertia.md",
    "Dimensions/Response Set Overlap.md",
    "Parametric Design Space.md",
    "Literature Mapping Process.md",
    "Key Transitions Between Paradigms.md",
    "Interference Control.md",
    "Derived Dimensions vs. Low-Level Parameters.md",
    "Cognitive Control.md",
    "Task Switching.md",
    "Theoretical Concepts",
    "Dimensions/Task Cue Type.md",
    "Papers",
    "Effects",
    "Dimensions/CSI (Cue-Stimulus Interval).md",
    "Dimensions",
    "Dimensions/Switch Rate.md",
    "Dimensions/N_Tasks.md",
    "Papers/Kiesel et al. (2010).md",
    "Effects/Switch Cost.md",
    "Effects/PRP Effect.md"
  ]
}